<annotation>
	<folder>MaskEdge</folder>
	<filename>img_edge_mask_97.jpg</filename>
	<path>..\EdgeImages\MaskEdge\img_edge_mask_97.jpg</path>
	<source>
		<database>Unknown</database>
	</source>
	<size>
		<width>500</width>
		<height>500</height>
		<depth>1</depth>
	</size>
	<segmented>0</segmented>
	<object>
		<name>mask</name>
		<pose>Unspecified</pose>
		<truncated>0</truncated>
		<difficult>0</difficult>
		<bndbox>
			<xmin>146</xmin>
			<ymin>257</ymin>
			<xmax>386</xmax>
			<ymax>433</ymax>
		</bndbox>
	</object>
</annotation>
